smartcast/__init__.py
smartcast-0.2.0.dist-info/LICENSE
smartcast-0.2.0.dist-info/METADATA
smartcast-0.2.0.dist-info/WHEEL
smartcast-0.2.0.dist-info/top_level.txt
smartcast-0.2.0.dist-info/RECORD
