Metadata-Version: 2.1
Name: smartcast
Version: 0.2.0
Summary: Recursively cast json to python dataclasses, typing, and class. Also provides reverse.
Home-page: https://github.com/qhpea/smartcast
Author: QHPEA
Author-email: oss@qhpea.org
License: UNKNOWN
Project-URL: Bug Tracker, https://github.com/qhpea/smartcast/issues
Platform: UNKNOWN
Classifier: Programming Language :: Python :: 3
Classifier: License :: OSI Approved :: MIT License
Classifier: Operating System :: OS Independent
Requires-Python: >=3.7,<3.10
License-File: LICENSE
